{"catalog.md":"CJiDebFz","components.md":"C-cC37rn","content.md":"DRFrfweC","data.md":"zPUDWCmK","eodash.md":"ohATkfNP","features_client-side-rendering.md":"CKJBcyzM","features_customizable-themes.md":"Bc5pHg7p","features_endpoint-integration.md":"CeO4BoEm","features_index.md":"5EAPzQfQ","features_process-definition.md":"CAwYy3KI","features_web-component.md":"DHiXBq-q","features_widget-extension.md":"CefvsNmt","first_steps.md":"DCdbKNV9","index.md":"D5lZfCZ2","preamble.md":"BN09A4v3","processing.md":"BP4Ff3g7","processing_inputs.md":"DWhbI9o6","roadmap.md":"CJQHScAl","storytelling.md":"iDRM-b14","styling.md":"BRZQI1xR","technology.md":"VdNifx-V","welcome.md":"eT9dlI_0"}
